[
  {
    "fighter": "volkan-oezdemir",
    "fighterName": "Volkan Oezdemir",
    "categoryId": "light-heavyweight",
    "categoryName": "Light Heavyweight",
    "currentPosition": 9,
    "previousPosition": 0,
    "date": "2023-02-23T04:18:04.909Z"
  },
  {
    "fighter": "ryan-spann",
    "fighterName": "Ryan Spann",
    "categoryId": "light-heavyweight",
    "categoryName": "Light Heavyweight",
    "currentPosition": 8,
    "previousPosition": 0,
    "date": "2023-02-23T04:18:04.909Z"
  },
  {
    "fighter": "derrick-lewis",
    "fighterName": "Derrick Lewis",
    "categoryId": "heavyweight",
    "categoryName": "Heavyweight",
    "currentPosition": 10,
    "previousPosition": 9,
    "date": "2023-02-16T09:22:53.901Z"
  },
  {
    "fighter": "marcin-tybura",
    "fighterName": "Marcin Tybura",
    "categoryId": "heavyweight",
    "categoryName": "Heavyweight",
    "currentPosition": 9,
    "previousPosition": 10,
    "date": "2023-02-16T09:22:53.901Z"
  },
  {
    "fighter": "alexander-volkov",
    "fighterName": "Alexander Volkov",
    "categoryId": "heavyweight",
    "categoryName": "Heavyweight",
    "currentPosition": 7,
    "previousPosition": 6,
    "date": "2023-02-16T09:22:53.901Z"
  },
  {
    "fighter": "sergey-spivak-0",
    "fighterName": "Serghei Spivac",
    "categoryId": "heavyweight",
    "categoryName": "Heavyweight",
    "currentPosition": 6,
    "previousPosition": 7,
    "date": "2023-02-16T09:22:53.901Z"
  },
  {
    "fighter": "michel-pereira",
    "fighterName": "Michel Pereira",
    "categoryId": "welterweight",
    "categoryName": "Welterweight",
    "currentPosition": 15,
    "previousPosition": 14,
    "date": "2023-02-16T09:22:53.901Z"
  },
  {
    "fighter": "sara-elpar-0",
    "fighterName": "Jack Della Maddalena",
    "categoryId": "welterweight",
    "categoryName": "Welterweight",
    "currentPosition": 14,
    "previousPosition": "unranked",
    "date": "2023-02-16T09:22:53.901Z"
  },
  {
    "fighter": "michael-chiesa",
    "fighterName": "Michael Chiesa",
    "categoryId": "welterweight",
    "categoryName": "Welterweight",
    "currentPosition": 13,
    "previousPosition": 12,
    "date": "2023-02-16T09:22:53.901Z"
  },
  {
    "fighter": "neil-magny",
    "fighterName": "Neil Magny",
    "categoryId": "welterweight",
    "categoryName": "Welterweight",
    "currentPosition": 12,
    "previousPosition": 13,
    "date": "2023-02-16T09:22:53.901Z"
  }
]